lazyad/__init__.py
lazyad/crawlers/__init__.py
lazyad/crawlers/chuangliang.py
lazyad/crawlers/mintegral.py
lazyad/crawlers/oceanengine.py
lazyad/crawlers/qq.py
lazyad/crawlers/wshoto.py
lazyad/open/__init__.py
lazyad/open/apple.py
lazyad/open/applovin.py
lazyad/open/kuaishou.py
lazyad/open/mintegral.py
lazyad/open/qq.py
lazyad/open/unity.py
lazyad-0.0.109.dist-info/METADATA
lazyad-0.0.109.dist-info/WHEEL
lazyad-0.0.109.dist-info/RECORD
