Metadata-Version: 2.4
Name: lazyad
Version: 0.0.109
Summary: make it easy to use ad api
Project-URL: Homepage, https://gitee.com/ZeroSeeker/lazyad
Project-URL: Issues, https://gitee.com/ZeroSeeker/lazyad/issues
Author-email: ZeroSeeker <zeroseeker@foxmail.com>
License-Expression: MIT
Classifier: Operating System :: OS Independent
Classifier: Programming Language :: Python :: 3
Requires-Python: >=3.8
Requires-Dist: lazysdk>=0.1.88
Requires-Dist: xmltodict==0.15.0
